{"userProfileId": 8420505, "totalKilocalories": 1964.0, "activeKilocalories": 170.0, "bmrKilocalories": 1794.0, "wellnessKilocalories": 1964.0, "burnedKilocalories": null, "consumedKilocalories": null, "remainingKilocalories": 1964.0, "totalSteps": 1480, "netCalorieGoal": null, "totalDistanceMeters": 1146, "wellnessDistanceMeters": 1146, "wellnessActiveKilocalories": 170.0, "netRemainingKilocalories": 170.0, "userDailySummaryId": 8420505, "calendarDate": "2022-05-30", "rule": {"typeId": 3, "typeKey": "subscribers"}, "uuid": "714cfc4b3b5f4f769e388c82c14af98e", "dailyStepGoal": 7360, "wellnessStartTimeGmt": "2022-05-29T14:00:00.0", "wellnessStartTimeLocal": "2022-05-30T00:00:00.0", "wellnessEndTimeGmt": "2022-05-30T14:00:00.0", "wellnessEndTimeLocal": "2022-05-31T00:00:00.0", "durationInMilliseconds": 86400000, "wellnessDescription": null, "highlyActiveSeconds": 930, "activeSeconds": 1854, "sedentarySeconds": 73296, "sleepingSeconds": 10320, "includesWellnessData": true, "includesActivityData": false, "includesCalorieConsumedData": false, "privacyProtected": false, "moderateIntensityMinutes": 0, "vigorousIntensityMinutes": 0, "floorsAscendedInMeters": 0.0, "floorsDescendedInMeters": 0.0, "floorsAscended": 0.0, "floorsDescended": 0.0, "intensityMinutesGoal": 150, "userFloorsAscendedGoal": 10, "minHeartRate": 48, "maxHeartRate": 124, "restingHeartRate": 57, "lastSevenDaysAvgRestingHeartRate": 58, "source": "GARMIN", "averageStressLevel": 30, "maxStressLevel": 96, "stressDuration": 20880, "restStressDuration": 24060, "activityStressDuration": 5400, "uncategorizedStressDuration": 36060, "totalStressDuration": 86400, "lowStressDuration": 13200, "mediumStressDuration": 5100, "highStressDuration": 2580, "stressPercentage": 24.17, "restStressPercentage": 27.85, "activityStressPercentage": 6.25, "uncategorizedStressPercentage": 41.74, "lowStressPercentage": 15.28, "mediumStressPercentage": 5.9, "highStressPercentage": 2.99, "stressQualifier": "CALM_AWAKE", "measurableAwakeDuration": 49380, "measurableAsleepDuration": 960, "lastSyncTimestampGMT": null, "minAvgHeartRate": 49, "maxAvgHeartRate": 123, "bodyBatteryChargedValue": null, "bodyBatteryDrainedValue": null, "bodyBatteryHighestValue": null, "bodyBatteryLowestValue": null, "bodyBatteryMostRecentValue": null, "bodyBatteryDuringSleep": null, "bodyBatteryVersion": null, "abnormalHeartRateAlertsCount": null, "averageSpo2": null, "lowestSpo2": null, "latestSpo2": null, "latestSpo2ReadingTimeGmt": null, "latestSpo2ReadingTimeLocal": null, "averageMonitoringEnvironmentAltitude": null, "restingCaloriesFromActivity": null}