{"userProfileId": 8420505, "totalKilocalories": 1937.0, "activeKilocalories": 112.0, "bmrKilocalories": 1825.0, "wellnessKilocalories": 1937.0, "burnedKilocalories": null, "consumedKilocalories": null, "remainingKilocalories": 1937.0, "totalSteps": 3224, "netCalorieGoal": null, "totalDistanceMeters": 2555, "wellnessDistanceMeters": 2555, "wellnessActiveKilocalories": 112.0, "netRemainingKilocalories": 112.0, "userDailySummaryId": 8420505, "calendarDate": "2022-12-20", "rule": {"typeId": 3, "typeKey": "subscribers"}, "uuid": "e41c4cca251c41d7be3b71f8ffda0627", "dailyStepGoal": 8250, "totalPushDistance": 0, "totalPushes": 0, "wellnessStartTimeGmt": "2022-12-19T13:00:00.0", "wellnessStartTimeLocal": "2022-12-20T00:00:00.0", "wellnessEndTimeGmt": "2022-12-20T13:00:00.0", "wellnessEndTimeLocal": "2022-12-21T00:00:00.0", "durationInMilliseconds": 86400000, "wellnessDescription": null, "highlyActiveSeconds": 1947, "activeSeconds": 2954, "sedentarySeconds": 48139, "sleepingSeconds": 33360, "includesWellnessData": true, "includesActivityData": false, "includesCalorieConsumedData": false, "privacyProtected": false, "moderateIntensityMinutes": 0, "vigorousIntensityMinutes": 0, "floorsAscendedInMeters": 5.132, "floorsDescendedInMeters": 7.915, "floorsAscended": 1.68373, "floorsDescended": 2.59678, "intensityMinutesGoal": 150, "userFloorsAscendedGoal": 10, "minHeartRate": 47, "maxHeartRate": 116, "restingHeartRate": 56, "lastSevenDaysAvgRestingHeartRate": 59, "source": "GARMIN", "averageStressLevel": 21, "maxStressLevel": 84, "stressDuration": 18600, "restStressDuration": 51480, "activityStressDuration": 7440, "uncategorizedStressDuration": 8340, "totalStressDuration": 85860, "lowStressDuration": 13440, "mediumStressDuration": 4740, "highStressDuration": 420, "stressPercentage": 21.66, "restStressPercentage": 59.96, "activityStressPercentage": 8.67, "uncategorizedStressPercentage": 9.71, "lowStressPercentage": 15.65, "mediumStressPercentage": 5.52, "highStressPercentage": 0.49, "stressQualifier": "BALANCED", "measurableAwakeDuration": 45240, "measurableAsleepDuration": 32280, "lastSyncTimestampGMT": null, "minAvgHeartRate": 49, "maxAvgHeartRate": 114, "bodyBatteryChargedValue": null, "bodyBatteryDrainedValue": null, "bodyBatteryHighestValue": null, "bodyBatteryLowestValue": null, "bodyBatteryMostRecentValue": null, "bodyBatteryDuringSleep": null, "bodyBatteryVersion": null, "abnormalHeartRateAlertsCount": null, "averageSpo2": null, "lowestSpo2": null, "latestSpo2": null, "latestSpo2ReadingTimeGmt": null, "latestSpo2ReadingTimeLocal": null, "averageMonitoringEnvironmentAltitude": null, "restingCaloriesFromActivity": null}