{"dailySleepDTO": {"id": 1589540280000, "userProfilePK": 8420505, "calendarDate": "2020-05-16", "sleepTimeSeconds": 42240, "napTimeSeconds": 0, "sleepWindowConfirmed": true, "sleepWindowConfirmationType": "enhanced_confirmed", "sleepStartTimestampGMT": 1589540280000, "sleepEndTimestampGMT": 1589584440000, "sleepStartTimestampLocal": 1589576280000, "sleepEndTimestampLocal": 1589620440000, "autoSleepStartTimestampGMT": 1589544720000, "autoSleepEndTimestampGMT": 1589576220000, "sleepQualityTypePK": null, "sleepResultTypePK": null, "unmeasurableSleepSeconds": 0, "deepSleepSeconds": 0, "lightSleepSeconds": 31920, "remSleepSeconds": 10320, "awakeSleepSeconds": 1920, "deviceRemCapable": true, "retro": false}, "sleepMovement": null, "remSleepData": true, "sleepLevels": null, "skinTempDataExists": false, "restingHeartRate": 56}