{"dailySleepDTO": {"id": 1642853100000, "userProfilePK": 8420505, "calendarDate": "2022-01-23", "sleepTimeSeconds": 31560, "napTimeSeconds": 0, "sleepWindowConfirmed": true, "sleepWindowConfirmationType": "enhanced_confirmed_final", "sleepStartTimestampGMT": 1642853100000, "sleepEndTimestampGMT": 1642884780000, "sleepStartTimestampLocal": 1642892700000, "sleepEndTimestampLocal": 1642924380000, "autoSleepStartTimestampGMT": 1642852740000, "autoSleepEndTimestampGMT": 1642883160000, "sleepQualityTypePK": null, "sleepResultTypePK": null, "unmeasurableSleepSeconds": 0, "deepSleepSeconds": 2880, "lightSleepSeconds": 21780, "remSleepSeconds": 6900, "awakeSleepSeconds": 120, "deviceRemCapable": true, "retro": false}, "sleepMovement": null, "remSleepData": true, "sleepLevels": null, "skinTempDataExists": false, "restingHeartRate": 56}