{"dailySleepDTO": {"id": 1506001020000, "userProfilePK": 8420505, "calendarDate": "2017-09-22", "sleepTimeSeconds": 33120, "napTimeSeconds": 0, "sleepWindowConfirmed": true, "sleepWindowConfirmationType": "auto_confirmed", "sleepStartTimestampGMT": 1506001020000, "sleepEndTimestampGMT": 1506034140000, "sleepStartTimestampLocal": 1506037020000, "sleepEndTimestampLocal": 1506070140000, "autoSleepStartTimestampGMT": 1506001020000, "autoSleepEndTimestampGMT": 1506034140000, "sleepQualityTypePK": null, "sleepResultTypePK": null, "unmeasurableSleepSeconds": null, "deepSleepSeconds": null, "lightSleepSeconds": null, "remSleepSeconds": null, "awakeSleepSeconds": null, "deviceRemCapable": false, "retro": false}, "sleepMovement": [], "remSleepData": null, "sleepLevels": [], "skinTempDataExists": false, "restingHeartRate": 59}