{"dailySleepDTO": {"id": 1656162840000, "userProfilePK": 8420505, "calendarDate": "2022-06-26", "sleepTimeSeconds": 33660, "napTimeSeconds": 0, "sleepWindowConfirmed": true, "sleepWindowConfirmationType": "enhanced_confirmed_final", "sleepStartTimestampGMT": 1656162840000, "sleepEndTimestampGMT": 1656196920000, "sleepStartTimestampLocal": 1656198840000, "sleepEndTimestampLocal": 1656232920000, "autoSleepStartTimestampGMT": 1656162000000, "autoSleepEndTimestampGMT": 1656195120000, "sleepQualityTypePK": null, "sleepResultTypePK": null, "unmeasurableSleepSeconds": 0, "deepSleepSeconds": 3960, "lightSleepSeconds": 20520, "remSleepSeconds": 9180, "awakeSleepSeconds": 420, "deviceRemCapable": true, "retro": false}, "sleepMovement": null, "remSleepData": true, "sleepLevels": null, "skinTempDataExists": false, "restingHeartRate": 56}