{"dailySleepDTO": {"id": 1661255640000, "userProfilePK": 8420505, "calendarDate": "2022-08-24", "sleepTimeSeconds": 31560, "napTimeSeconds": 0, "sleepWindowConfirmed": true, "sleepWindowConfirmationType": "enhanced_confirmed", "sleepStartTimestampGMT": 1661255640000, "sleepEndTimestampGMT": 1661287920000, "sleepStartTimestampLocal": 1661291640000, "sleepEndTimestampLocal": 1661323920000, "autoSleepStartTimestampGMT": 1661257800000, "autoSleepEndTimestampGMT": 1661289120000, "sleepQualityTypePK": null, "sleepResultTypePK": null, "unmeasurableSleepSeconds": 0, "deepSleepSeconds": 3300, "lightSleepSeconds": 21600, "remSleepSeconds": 6660, "awakeSleepSeconds": 720, "deviceRemCapable": true, "retro": false}, "sleepMovement": null, "remSleepData": true, "sleepLevels": null, "skinTempDataExists": false, "restingHeartRate": 57}