{"dailySleepDTO": {"id": 1708727700000, "userProfilePK": 8420505, "calendarDate": "2024-02-24", "sleepTimeSeconds": 14040, "napTimeSeconds": 0, "sleepWindowConfirmed": true, "sleepWindowConfirmationType": "enhanced_confirmed_final", "sleepStartTimestampGMT": 1708727700000, "sleepEndTimestampGMT": 1708749360000, "sleepStartTimestampLocal": 1708731300000, "sleepEndTimestampLocal": 1708752960000, "autoSleepStartTimestampGMT": null, "autoSleepEndTimestampGMT": null, "sleepQualityTypePK": null, "sleepResultTypePK": null, "unmeasurableSleepSeconds": 0, "deepSleepSeconds": 1800, "lightSleepSeconds": 10920, "remSleepSeconds": 1320, "awakeSleepSeconds": 7620, "deviceRemCapable": true, "retro": false, "sleepFromDevice": true, "averageSpO2Value": 93.0, "lowestSpO2Value": 90, "highestSpO2Value": 96, "averageSpO2HRSleep": 58.0, "averageRespirationValue": 15.0, "lowestRespirationValue": 11.0, "highestRespirationValue": 19.0, "awakeCount": 4, "avgSleepStress": 12.0, "ageGroup": "ADULT", "sleepScoreFeedback": "NEGATIVE_SHORT_AND_POOR_STRUCTURE", "sleepScoreInsight": "NONE", "sleepScorePersonalizedInsight": "GENERAL_NEG_FAIR_OR_POOR_SLEEP", "sleepScores": {"totalDuration": {"qualifierKey": "POOR", "optimalStart": 28800.0, "optimalEnd": 28800.0}, "stress": {"qualifierKey": "EXCELLENT", "optimalStart": 0.0, "optimalEnd": 15.0}, "awakeCount": {"qualifierKey": "POOR", "optimalStart": 0.0, "optimalEnd": 1.0}, "overall": {"value": 41, "qualifierKey": "POOR"}, "remPercentage": {"value": 9, "qualifierKey": "POOR", "optimalStart": 21.0, "optimalEnd": 31.0, "idealStartInSeconds": 2948.4, "idealEndInSeconds": 4352.4}, "restlessness": {"qualifierKey": "POOR", "optimalStart": 0.0, "optimalEnd": 5.0}, "lightPercentage": {"value": 78, "qualifierKey": "FAIR", "optimalStart": 30.0, "optimalEnd": 64.0, "idealStartInSeconds": 4212.0, "idealEndInSeconds": 8985.6}, "deepPercentage": {"value": 13, "qualifierKey": "FAIR", "optimalStart": 16.0, "optimalEnd": 33.0, "idealStartInSeconds": 2246.4, "idealEndInSeconds": 4633.2}}, "sleepVersion": 2}, "sleepMovement": null, "remSleepData": true, "sleepLevels": null, "wellnessSpO2SleepSummaryDTO": {"userProfilePk": 8420505, "deviceId": 3447302851, "sleepMeasurementStartGMT": "2024-02-23T22:40:00.0", "sleepMeasurementEndGMT": "2024-02-24T04:36:00.0", "alertThresholdValue": null, "numberOfEventsBelowThreshold": null, "durationOfEventsBelowThreshold": null, "averageSPO2": 93.0, "averageSpO2HR": 58.0, "lowestSPO2": 90}, "skinTempDataExists": true, "avgSkinTempDeviationC": -0.7, "avgSkinTempDeviationF": -1.3, "bodyBatteryChange": 31, "skinTempCalibrationDays": 19, "restingHeartRate": 52}