{"dailySleepDTO": {"id": 1698440100000, "userProfilePK": 8420505, "calendarDate": "2023-10-28", "sleepTimeSeconds": 34020, "napTimeSeconds": 0, "sleepWindowConfirmed": true, "sleepWindowConfirmationType": "enhanced_confirmed_final", "sleepStartTimestampGMT": 1698440100000, "sleepEndTimestampGMT": 1698474120000, "sleepStartTimestampLocal": 1698447300000, "sleepEndTimestampLocal": 1698481320000, "autoSleepStartTimestampGMT": 1698439740000, "autoSleepEndTimestampGMT": 1698473160000, "sleepQualityTypePK": null, "sleepResultTypePK": null, "unmeasurableSleepSeconds": 0, "deepSleepSeconds": 2700, "lightSleepSeconds": 25020, "remSleepSeconds": 6300, "awakeSleepSeconds": 0, "deviceRemCapable": true, "retro": false}, "sleepMovement": null, "remSleepData": true, "sleepLevels": null, "skinTempDataExists": false, "restingHeartRate": 60}