{"dailySleepDTO": {"id": 1632833400000, "userProfilePK": 8420505, "calendarDate": "2021-09-29", "sleepTimeSeconds": 33060, "napTimeSeconds": 0, "sleepWindowConfirmed": true, "sleepWindowConfirmationType": "enhanced_confirmed", "sleepStartTimestampGMT": 1632833400000, "sleepEndTimestampGMT": 1632867420000, "sleepStartTimestampLocal": 1632869400000, "sleepEndTimestampLocal": 1632903420000, "autoSleepStartTimestampGMT": 1632831900000, "autoSleepEndTimestampGMT": 1632862920000, "sleepQualityTypePK": null, "sleepResultTypePK": null, "unmeasurableSleepSeconds": 900, "deepSleepSeconds": 1860, "lightSleepSeconds": 22380, "remSleepSeconds": 8820, "awakeSleepSeconds": 60, "deviceRemCapable": true, "retro": false}, "sleepMovement": null, "remSleepData": true, "sleepLevels": null, "skinTempDataExists": false, "restingHeartRate": 59}