{"activityId":6044416389,"activityUUID":{"uuid":"512e52c9-f8c1-45cc-b11d-7f2dc908834f"},"activityName":"Melbourne Running","userProfileId":8420505,"isMultiSportParent":false,"activityTypeDTO":{"typeId":1,"typeKey":"running","parentTypeId":17,"isHidden":false,"sortOrder":null,"restricted":false,"trimmable":true},"eventTypeDTO":{"typeId":9,"typeKey":"uncategorized","sortOrder":10},"accessControlRuleDTO":{"typeId":3,"typeKey":"subscribers"},"timeZoneUnitDTO":{"unitId":140,"unitKey":"Australia/Sydney","factor":0.0,"timeZone":"Australia/Sydney"},"metadataDTO":{"isOriginal":true,"deviceApplicationInstallationId":878246,"agentApplicationInstallationId":null,"agentString":null,"fileFormat":{"formatId":7,"formatKey":"fit"},"associatedCourseId":null,"lastUpdateDate":"2021-01-03T02:00:11.0","uploadedDate":"2021-01-03T02:00:11.0","videoUrl":null,"hasPolyline":true,"hasChartData":true,"hasHrTimeInZones":true,"hasPowerTimeInZones":false,"userInfoDto":{"userProfilePk":8420505,"displayname":"jamesmstone","fullname":"James Stone","profileImageUrlLarge":null,"profileImageUrlMedium":"https://s3.amazonaws.com/garmin-connect-prod/profile_images/92130502-f92f-4d82-b8b4-aaa2bca84737-8420505.png","profileImageUrlSmall":"https://s3.amazonaws.com/garmin-connect-prod/profile_images/348f82e9-2c22-4924-8326-b1bf8b9f802e-8420505.png","userPro":false},"childIds":[],"childActivityTypes":[],"sensors":[],"activityImages":[],"manufacturer":"GARMIN","diveNumber":null,"lapCount":8,"associatedWorkoutId":null,"isAtpActivity":null,"deviceMetaDataDTO":{"deviceId":"3948023825","deviceTypePk":34256,"deviceVersionPk":878246},"hasIntensityIntervals":false,"hasSplits":false,"eBikeMaxAssistModes":null,"eBikeBatteryUsage":null,"eBikeBatteryRemaining":null,"eBikeAssistModeInfoDTOList":null,"calendarEventInfo":null,"manualActivity":false,"personalRecord":false,"gcj02":false,"autoCalcCalories":false,"favorite":false,"trimmed":false,"elevationCorrected":false},"summaryDTO":{"startTimeLocal":"2021-01-03T12:16:40.0","startTimeGMT":"2021-01-03T01:16:40.0","startLatitude":-37.99481922760606,"startLongitude":145.07483093999326,"distance":7755.91,"duration":1884.988,"movingDuration":1881.895,"elapsedDuration":1884.988,"elevationGain":12.0,"elevationLoss":27.0,"maxElevation":24.8,"minElevation":7.0,"averageSpeed":4.114999771118164,"averageMovingSpeed":4.121329936860602,"maxSpeed":5.888000011444092,"calories":299.0,"averageHR":139.0,"maxHR":159.0,"averageRunCadence":167.875,"maxRunCadence":184.0,"averageTemperature":24.475438041749154,"maxTemperature":26.0,"minTemperature":23.0,"strideLength":147.08258188313164,"trainingEffect":2.5,"anaerobicTrainingEffect":0.20000000298023224,"aerobicTrainingEffectMessage":"MAINTAINING_AEROBIC_FITNESS_1","anaerobicTrainingEffectMessage":"NO_ANAEROBIC_BENEFIT_0","endLatitude":-38.00189497880638,"endLongitude":145.07768698967993,"maxVerticalSpeed":0.4000005722045899,"minActivityLapDuration":182.965},"locationName":"Melbourne"}