{"activityId":8447737727,"activityUUID":{"uuid":"893dc95e-0558-439a-95d2-d27d7434d2bc"},"activityName":"Melbourne Running","userProfileId":8420505,"isMultiSportParent":false,"activityTypeDTO":{"typeId":1,"typeKey":"running","parentTypeId":17,"isHidden":false,"sortOrder":null,"restricted":false,"trimmable":true},"eventTypeDTO":{"typeId":9,"typeKey":"uncategorized","sortOrder":10},"accessControlRuleDTO":{"typeId":3,"typeKey":"subscribers"},"timeZoneUnitDTO":{"unitId":140,"unitKey":"Australia/Sydney","factor":0.0,"timeZone":"Australia/Sydney"},"metadataDTO":{"isOriginal":true,"deviceApplicationInstallationId":898492,"agentApplicationInstallationId":null,"agentString":null,"fileFormat":{"formatId":7,"formatKey":"fit"},"associatedCourseId":null,"lastUpdateDate":"2022-03-13T08:04:25.0","uploadedDate":"2022-03-13T08:04:24.0","videoUrl":null,"hasPolyline":true,"hasChartData":true,"hasHrTimeInZones":true,"hasPowerTimeInZones":false,"userInfoDto":{"userProfilePk":8420505,"displayname":"jamesmstone","fullname":"James Stone","profileImageUrlLarge":null,"profileImageUrlMedium":"https://s3.amazonaws.com/garmin-connect-prod/profile_images/92130502-f92f-4d82-b8b4-aaa2bca84737-8420505.png","profileImageUrlSmall":"https://s3.amazonaws.com/garmin-connect-prod/profile_images/348f82e9-2c22-4924-8326-b1bf8b9f802e-8420505.png","userPro":false},"childIds":[],"childActivityTypes":[],"sensors":[],"activityImages":[],"manufacturer":"GARMIN","diveNumber":null,"lapCount":22,"associatedWorkoutId":null,"isAtpActivity":null,"deviceMetaDataDTO":{"deviceId":"3948023825","deviceTypePk":34256,"deviceVersionPk":898492},"hasIntensityIntervals":false,"hasSplits":false,"eBikeMaxAssistModes":null,"eBikeBatteryUsage":null,"eBikeBatteryRemaining":null,"eBikeAssistModeInfoDTOList":null,"calendarEventInfo":null,"personalRecord":false,"autoCalcCalories":false,"favorite":false,"gcj02":false,"runPowerWindDataEnabled":null,"manualActivity":false,"trimmed":false,"elevationCorrected":false},"summaryDTO":{"startTimeLocal":"2022-03-13T10:25:08.0","startTimeGMT":"2022-03-12T23:25:08.0","startLatitude":-37.99454530701041,"startLongitude":145.07457084953785,"distance":21199.86,"duration":5610.478,"movingDuration":5593.261,"elapsedDuration":6266.341,"elevationGain":27.0,"elevationLoss":37.0,"maxElevation":41.8,"minElevation":26.2,"averageSpeed":3.7790000438690186,"averageMovingSpeed":3.7902503332108406,"maxSpeed":4.730999946594238,"calories":980.0,"averageHR":156.0,"maxHR":192.0,"averageRunCadence":166.28125,"maxRunCadence":190.0,"averageTemperature":26.586601170553752,"maxTemperature":30.0,"minTemperature":23.0,"strideLength":136.36627521407044,"trainingEffect":4.0,"anaerobicTrainingEffect":1.600000023841858,"aerobicTrainingEffectMessage":"HIGHLY_IMPROVING_LACTATE_THRESHOLD_13","anaerobicTrainingEffectMessage":"MINOR_ANAEROBIC_BENEFIT_15","endLatitude":-38.00184393301606,"endLongitude":145.07786829024553,"maxVerticalSpeed":0.7999992370605469,"minActivityLapDuration":47.531},"locationName":"Melbourne"}