{"userProfileId": 8420505, "totalKilocalories": 1980.0, "activeKilocalories": 174.0, "bmrKilocalories": 1806.0, "wellnessKilocalories": 1980.0, "burnedKilocalories": null, "consumedKilocalories": null, "remainingKilocalories": 1980.0, "totalSteps": 6349, "netCalorieGoal": null, "totalDistanceMeters": 5014, "wellnessDistanceMeters": 5014, "wellnessActiveKilocalories": 174.0, "netRemainingKilocalories": 174.0, "userDailySummaryId": 8420505, "calendarDate": "2023-10-06", "rule": {"typeId": 3, "typeKey": "subscribers"}, "uuid": "de36985782e447ac8e8ebd7cf81c61c8", "dailyStepGoal": 9890, "wellnessStartTimeGmt": "2023-10-05T22:00:00.0", "wellnessStartTimeLocal": "2023-10-06T00:00:00.0", "wellnessEndTimeGmt": "2023-10-06T22:00:00.0", "wellnessEndTimeLocal": "2023-10-07T00:00:00.0", "durationInMilliseconds": 86400000, "wellnessDescription": null, "highlyActiveSeconds": 2677, "activeSeconds": 3483, "sedentarySeconds": 51740, "sleepingSeconds": 28500, "includesWellnessData": true, "includesActivityData": false, "includesCalorieConsumedData": false, "privacyProtected": false, "moderateIntensityMinutes": 0, "vigorousIntensityMinutes": 0, "floorsAscendedInMeters": 10.734, "floorsDescendedInMeters": 17.551, "floorsAscended": 3.52165, "floorsDescended": 5.7582, "intensityMinutesGoal": 150, "userFloorsAscendedGoal": 10, "minHeartRate": 45, "maxHeartRate": 120, "restingHeartRate": 55, "lastSevenDaysAvgRestingHeartRate": 54, "source": "GARMIN", "averageStressLevel": 32, "maxStressLevel": 87, "stressDuration": 29160, "restStressDuration": 25260, "activityStressDuration": 9840, "uncategorizedStressDuration": 21780, "totalStressDuration": 86040, "lowStressDuration": 20160, "mediumStressDuration": 7740, "highStressDuration": 1260, "stressPercentage": 33.89, "restStressPercentage": 29.36, "activityStressPercentage": 11.44, "uncategorizedStressPercentage": 25.31, "lowStressPercentage": 23.43, "mediumStressPercentage": 9.0, "highStressPercentage": 1.46, "stressQualifier": "BALANCED", "measurableAwakeDuration": 47340, "measurableAsleepDuration": 16920, "lastSyncTimestampGMT": null, "minAvgHeartRate": 46, "maxAvgHeartRate": 119, "bodyBatteryChargedValue": null, "bodyBatteryDrainedValue": null, "bodyBatteryHighestValue": null, "bodyBatteryLowestValue": null, "bodyBatteryMostRecentValue": null, "bodyBatteryDuringSleep": null, "bodyBatteryVersion": null, "abnormalHeartRateAlertsCount": null, "averageSpo2": null, "lowestSpo2": null, "latestSpo2": null, "latestSpo2ReadingTimeGmt": null, "latestSpo2ReadingTimeLocal": null, "averageMonitoringEnvironmentAltitude": null, "restingCaloriesFromActivity": null}