{"startDate": "2024-08-27", "endDate": "2024-08-27", "dateWeightList": [{"samplePk": 1724776577873, "date": 1724783770961, "calendarDate": "2024-08-27", "weight": 51500.0, "bmi": null, "bodyFat": null, "bodyWater": null, "boneMass": null, "muscleMass": null, "physiqueRating": null, "visceralFat": null, "metabolicAge": null, "sourceType": "MANUAL", "timestampGMT": 1724776570961, "weightDelta": null}], "totalAverage": {"from": 1724716800000, "until": 1724803199999, "weight": 51500.0, "bmi": null, "bodyFat": null, "bodyWater": null, "boneMass": null, "muscleMass": null, "physiqueRating": null, "visceralFat": null, "metabolicAge": null}}