{"userProfileId": 8420505, "totalKilocalories": 2744.0, "activeKilocalories": 944.0, "bmrKilocalories": 1800.0, "wellnessKilocalories": 2744.0, "burnedKilocalories": null, "consumedKilocalories": null, "remainingKilocalories": 2744.0, "totalSteps": 8937, "netCalorieGoal": null, "totalDistanceMeters": 25999, "wellnessDistanceMeters": 8869, "wellnessActiveKilocalories": 944.0, "netRemainingKilocalories": 944.0, "userDailySummaryId": 8420505, "calendarDate": "2021-02-27", "rule": {"typeId": 3, "typeKey": "subscribers"}, "uuid": "cd08fbbbdc0244c2bd75b35b4d4081ff", "dailyStepGoal": 6150, "wellnessStartTimeGmt": "2021-02-26T13:00:00.0", "wellnessStartTimeLocal": "2021-02-27T00:00:00.0", "wellnessEndTimeGmt": "2021-02-27T13:00:00.0", "wellnessEndTimeLocal": "2021-02-28T00:00:00.0", "durationInMilliseconds": 86400000, "wellnessDescription": null, "highlyActiveSeconds": 2641, "activeSeconds": 3993, "sedentarySeconds": 43826, "sleepingSeconds": 35940, "includesWellnessData": true, "includesActivityData": true, "includesCalorieConsumedData": false, "privacyProtected": false, "moderateIntensityMinutes": 41, "vigorousIntensityMinutes": 72, "floorsAscendedInMeters": 38.493, "floorsDescendedInMeters": 50.949, "floorsAscended": 12.62894, "floorsDescended": 16.71555, "intensityMinutesGoal": 150, "userFloorsAscendedGoal": 10, "minHeartRate": 36, "maxHeartRate": 208, "restingHeartRate": 52, "lastSevenDaysAvgRestingHeartRate": 53, "source": "GARMIN", "averageStressLevel": 22, "maxStressLevel": 92, "stressDuration": 18720, "restStressDuration": 43140, "activityStressDuration": 12180, "uncategorizedStressDuration": 11460, "totalStressDuration": 85500, "lowStressDuration": 8700, "mediumStressDuration": 8100, "highStressDuration": 1920, "stressPercentage": 21.89, "restStressPercentage": 50.46, "activityStressPercentage": 14.25, "uncategorizedStressPercentage": 13.4, "lowStressPercentage": 10.18, "mediumStressPercentage": 9.47, "highStressPercentage": 2.25, "stressQualifier": "BALANCED", "measurableAwakeDuration": 40140, "measurableAsleepDuration": 33900, "lastSyncTimestampGMT": null, "minAvgHeartRate": 37, "maxAvgHeartRate": 201, "bodyBatteryChargedValue": null, "bodyBatteryDrainedValue": null, "bodyBatteryHighestValue": null, "bodyBatteryLowestValue": null, "bodyBatteryMostRecentValue": null, "bodyBatteryDuringSleep": null, "bodyBatteryVersion": 1.0, "abnormalHeartRateAlertsCount": null, "averageSpo2": null, "lowestSpo2": null, "latestSpo2": null, "latestSpo2ReadingTimeGmt": null, "latestSpo2ReadingTimeLocal": null, "averageMonitoringEnvironmentAltitude": null, "restingCaloriesFromActivity": null}