{"userProfileId": 8420505, "totalKilocalories": 2282.0, "activeKilocalories": 482.0, "bmrKilocalories": 1800.0, "wellnessKilocalories": 2282.0, "burnedKilocalories": null, "consumedKilocalories": null, "remainingKilocalories": 2282.0, "totalSteps": 6885, "netCalorieGoal": null, "totalDistanceMeters": 5581, "wellnessDistanceMeters": 5581, "wellnessActiveKilocalories": 482.0, "netRemainingKilocalories": 482.0, "userDailySummaryId": 8420505, "calendarDate": "2021-11-16", "rule": {"typeId": 3, "typeKey": "subscribers"}, "uuid": "432cdbb1ab6e402aad617d45993c808a", "dailyStepGoal": 7440, "wellnessStartTimeGmt": "2021-11-15T13:00:00.0", "wellnessStartTimeLocal": "2021-11-16T00:00:00.0", "wellnessEndTimeGmt": "2021-11-16T13:00:00.0", "wellnessEndTimeLocal": "2021-11-17T00:00:00.0", "durationInMilliseconds": 86400000, "wellnessDescription": null, "highlyActiveSeconds": 1474, "activeSeconds": 5174, "sedentarySeconds": 53292, "sleepingSeconds": 26460, "includesWellnessData": true, "includesActivityData": false, "includesCalorieConsumedData": false, "privacyProtected": false, "moderateIntensityMinutes": 0, "vigorousIntensityMinutes": 0, "floorsAscendedInMeters": 73.152, "floorsDescendedInMeters": 56.994, "floorsAscended": 24.0, "floorsDescended": 18.69882, "intensityMinutesGoal": 150, "userFloorsAscendedGoal": 10, "minHeartRate": 47, "maxHeartRate": 150, "restingHeartRate": 54, "lastSevenDaysAvgRestingHeartRate": 55, "source": "GARMIN", "averageStressLevel": 38, "maxStressLevel": 93, "stressDuration": 37980, "restStressDuration": 31920, "activityStressDuration": 6840, "uncategorizedStressDuration": 9600, "totalStressDuration": 86340, "lowStressDuration": 12960, "mediumStressDuration": 18000, "highStressDuration": 7020, "stressPercentage": 43.99, "restStressPercentage": 36.97, "activityStressPercentage": 7.92, "uncategorizedStressPercentage": 11.12, "lowStressPercentage": 15.01, "mediumStressPercentage": 20.85, "highStressPercentage": 8.13, "stressQualifier": "BALANCED", "measurableAwakeDuration": 53040, "measurableAsleepDuration": 23700, "lastSyncTimestampGMT": null, "minAvgHeartRate": 47, "maxAvgHeartRate": 147, "bodyBatteryChargedValue": null, "bodyBatteryDrainedValue": null, "bodyBatteryHighestValue": null, "bodyBatteryLowestValue": null, "bodyBatteryMostRecentValue": null, "bodyBatteryDuringSleep": null, "bodyBatteryVersion": null, "abnormalHeartRateAlertsCount": null, "averageSpo2": null, "lowestSpo2": null, "latestSpo2": null, "latestSpo2ReadingTimeGmt": null, "latestSpo2ReadingTimeLocal": null, "averageMonitoringEnvironmentAltitude": null, "restingCaloriesFromActivity": null}