{"userProfileId": 8420505, "totalKilocalories": 2116.0, "activeKilocalories": 273.0, "bmrKilocalories": 1843.0, "wellnessKilocalories": 2116.0, "burnedKilocalories": null, "consumedKilocalories": null, "remainingKilocalories": 2116.0, "totalSteps": 11475, "netCalorieGoal": null, "totalDistanceMeters": 9037, "wellnessDistanceMeters": 9037, "wellnessActiveKilocalories": 273.0, "netRemainingKilocalories": 273.0, "userDailySummaryId": 8420505, "calendarDate": "2019-04-09", "rule": {"typeId": 3, "typeKey": "subscribers"}, "uuid": "471fd4f5d13b4d6ba8504ff23fbf60bb", "dailyStepGoal": 9370, "wellnessStartTimeGmt": "2019-04-08T14:00:00.0", "wellnessStartTimeLocal": "2019-04-09T00:00:00.0", "wellnessEndTimeGmt": "2019-04-09T14:00:00.0", "wellnessEndTimeLocal": "2019-04-10T00:00:00.0", "durationInMilliseconds": 86400000, "wellnessDescription": null, "highlyActiveSeconds": 3832, "activeSeconds": 3920, "sedentarySeconds": 50148, "sleepingSeconds": 28500, "includesWellnessData": true, "includesActivityData": false, "includesCalorieConsumedData": false, "privacyProtected": false, "moderateIntensityMinutes": 0, "vigorousIntensityMinutes": 0, "floorsAscendedInMeters": 35.211, "floorsDescendedInMeters": 52.467, "floorsAscended": 11.55217, "floorsDescended": 17.21358, "intensityMinutesGoal": 150, "userFloorsAscendedGoal": 10, "minHeartRate": 44, "maxHeartRate": 120, "restingHeartRate": 54, "lastSevenDaysAvgRestingHeartRate": 53, "source": "GARMIN", "averageStressLevel": 17, "maxStressLevel": 79, "stressDuration": 12840, "restStressDuration": 52920, "activityStressDuration": 8880, "uncategorizedStressDuration": 11580, "totalStressDuration": 86220, "lowStressDuration": 10380, "mediumStressDuration": 2280, "highStressDuration": 180, "stressPercentage": 14.89, "restStressPercentage": 61.38, "activityStressPercentage": 10.3, "uncategorizedStressPercentage": 13.43, "lowStressPercentage": 12.04, "mediumStressPercentage": 2.64, "highStressPercentage": 0.21, "stressQualifier": "CALM", "measurableAwakeDuration": 46140, "measurableAsleepDuration": 28500, "lastSyncTimestampGMT": null, "minAvgHeartRate": 45, "maxAvgHeartRate": 114, "bodyBatteryChargedValue": null, "bodyBatteryDrainedValue": null, "bodyBatteryHighestValue": null, "bodyBatteryLowestValue": null, "bodyBatteryMostRecentValue": null, "bodyBatteryDuringSleep": null, "bodyBatteryVersion": 1.0, "abnormalHeartRateAlertsCount": null, "averageSpo2": null, "lowestSpo2": null, "latestSpo2": null, "latestSpo2ReadingTimeGmt": null, "latestSpo2ReadingTimeLocal": null, "averageMonitoringEnvironmentAltitude": null, "restingCaloriesFromActivity": null}