{"userProfileId": 8420505, "totalKilocalories": 2210.0, "activeKilocalories": 367.0, "bmrKilocalories": 1843.0, "wellnessKilocalories": 2210.0, "burnedKilocalories": null, "consumedKilocalories": null, "remainingKilocalories": 2210.0, "totalSteps": 5639, "netCalorieGoal": null, "totalDistanceMeters": 4584, "wellnessDistanceMeters": 4584, "wellnessActiveKilocalories": 367.0, "netRemainingKilocalories": 367.0, "userDailySummaryId": 8420505, "calendarDate": "2019-11-17", "rule": {"typeId": 3, "typeKey": "subscribers"}, "uuid": "c4324fcaf5c641b08eacf440046d15e4", "dailyStepGoal": 5820, "wellnessStartTimeGmt": "2019-11-16T13:00:00.0", "wellnessStartTimeLocal": "2019-11-17T00:00:00.0", "wellnessEndTimeGmt": "2019-11-17T13:00:00.0", "wellnessEndTimeLocal": "2019-11-18T00:00:00.0", "durationInMilliseconds": 86400000, "wellnessDescription": null, "highlyActiveSeconds": 1738, "activeSeconds": 4766, "sedentarySeconds": 77016, "sleepingSeconds": 2880, "includesWellnessData": true, "includesActivityData": false, "includesCalorieConsumedData": false, "privacyProtected": false, "moderateIntensityMinutes": 0, "vigorousIntensityMinutes": 0, "floorsAscendedInMeters": 68.767, "floorsDescendedInMeters": 32.737, "floorsAscended": 22.56135, "floorsDescended": 10.74049, "intensityMinutesGoal": 150, "userFloorsAscendedGoal": 10, "minHeartRate": 49, "maxHeartRate": 152, "restingHeartRate": 63, "lastSevenDaysAvgRestingHeartRate": 59, "source": "GARMIN", "averageStressLevel": 31, "maxStressLevel": 94, "stressDuration": 9180, "restStressDuration": 11160, "activityStressDuration": 8880, "uncategorizedStressDuration": 57180, "totalStressDuration": 86400, "lowStressDuration": 5040, "mediumStressDuration": 3240, "highStressDuration": 900, "stressPercentage": 10.62, "restStressPercentage": 12.92, "activityStressPercentage": 10.28, "uncategorizedStressPercentage": 66.18, "lowStressPercentage": 5.83, "mediumStressPercentage": 3.75, "highStressPercentage": 1.04, "stressQualifier": "UNKNOWN", "measurableAwakeDuration": 25920, "measurableAsleepDuration": 3300, "lastSyncTimestampGMT": null, "minAvgHeartRate": 55, "maxAvgHeartRate": 137, "bodyBatteryChargedValue": null, "bodyBatteryDrainedValue": null, "bodyBatteryHighestValue": null, "bodyBatteryLowestValue": null, "bodyBatteryMostRecentValue": null, "bodyBatteryDuringSleep": null, "bodyBatteryVersion": 1.0, "abnormalHeartRateAlertsCount": null, "averageSpo2": null, "lowestSpo2": null, "latestSpo2": null, "latestSpo2ReadingTimeGmt": null, "latestSpo2ReadingTimeLocal": null, "averageMonitoringEnvironmentAltitude": null, "restingCaloriesFromActivity": null}