{"userProfileId": 8420505, "totalKilocalories": 2477.0, "activeKilocalories": 634.0, "bmrKilocalories": 1843.0, "wellnessKilocalories": 2477.0, "burnedKilocalories": null, "consumedKilocalories": null, "remainingKilocalories": 2477.0, "totalSteps": 16068, "netCalorieGoal": null, "totalDistanceMeters": 12907, "wellnessDistanceMeters": 12907, "wellnessActiveKilocalories": 634.0, "netRemainingKilocalories": 634.0, "userDailySummaryId": 8420505, "calendarDate": "2019-02-14", "rule": {"typeId": 3, "typeKey": "subscribers"}, "uuid": "b5a4fb62f6204cfd918c798938dc3a5a", "dailyStepGoal": 13710, "wellnessStartTimeGmt": "2019-02-13T13:00:00.0", "wellnessStartTimeLocal": "2019-02-14T00:00:00.0", "wellnessEndTimeGmt": "2019-02-14T13:00:00.0", "wellnessEndTimeLocal": "2019-02-15T00:00:00.0", "durationInMilliseconds": 86400000, "wellnessDescription": null, "highlyActiveSeconds": 5503, "activeSeconds": 4648, "sedentarySeconds": 48109, "sleepingSeconds": 28140, "includesWellnessData": true, "includesActivityData": false, "includesCalorieConsumedData": false, "privacyProtected": false, "moderateIntensityMinutes": 14, "vigorousIntensityMinutes": 19, "floorsAscendedInMeters": 52.02, "floorsDescendedInMeters": 51.839, "floorsAscended": 17.06693, "floorsDescended": 17.00755, "intensityMinutesGoal": 150, "userFloorsAscendedGoal": 10, "minHeartRate": 45, "maxHeartRate": 171, "restingHeartRate": 53, "lastSevenDaysAvgRestingHeartRate": 53, "source": "GARMIN", "averageStressLevel": 16, "maxStressLevel": 97, "stressDuration": 10860, "restStressDuration": 55800, "activityStressDuration": 9720, "uncategorizedStressDuration": 8340, "totalStressDuration": 84720, "lowStressDuration": 7440, "mediumStressDuration": 2820, "highStressDuration": 600, "stressPercentage": 12.82, "restStressPercentage": 65.86, "activityStressPercentage": 11.47, "uncategorizedStressPercentage": 9.84, "lowStressPercentage": 8.78, "mediumStressPercentage": 3.33, "highStressPercentage": 0.71, "stressQualifier": "CALM", "measurableAwakeDuration": 49020, "measurableAsleepDuration": 27360, "lastSyncTimestampGMT": null, "minAvgHeartRate": 46, "maxAvgHeartRate": 169, "bodyBatteryChargedValue": null, "bodyBatteryDrainedValue": null, "bodyBatteryHighestValue": null, "bodyBatteryLowestValue": null, "bodyBatteryMostRecentValue": null, "bodyBatteryDuringSleep": null, "bodyBatteryVersion": 1.0, "abnormalHeartRateAlertsCount": null, "averageSpo2": null, "lowestSpo2": null, "latestSpo2": null, "latestSpo2ReadingTimeGmt": null, "latestSpo2ReadingTimeLocal": null, "averageMonitoringEnvironmentAltitude": null, "restingCaloriesFromActivity": null}