{"userProfileId": 8420505, "totalKilocalories": 2042.0, "activeKilocalories": 223.0, "bmrKilocalories": 1819.0, "wellnessKilocalories": 2042.0, "burnedKilocalories": null, "consumedKilocalories": null, "remainingKilocalories": 2042.0, "totalSteps": 6036, "netCalorieGoal": null, "totalDistanceMeters": 4660, "wellnessDistanceMeters": 4660, "wellnessActiveKilocalories": 223.0, "netRemainingKilocalories": 223.0, "userDailySummaryId": 8420505, "calendarDate": "2018-03-09", "rule": {"typeId": 3, "typeKey": "subscribers"}, "uuid": "d385e475a7654d2cafa1edc42de9ded3", "dailyStepGoal": 9900, "wellnessStartTimeGmt": "2018-03-08T13:00:00.0", "wellnessStartTimeLocal": "2018-03-09T00:00:00.0", "wellnessEndTimeGmt": "2018-03-09T13:00:00.0", "wellnessEndTimeLocal": "2018-03-10T00:00:00.0", "durationInMilliseconds": 86400000, "wellnessDescription": null, "highlyActiveSeconds": 1523, "activeSeconds": 3099, "sedentarySeconds": 53698, "sleepingSeconds": 28080, "includesWellnessData": true, "includesActivityData": false, "includesCalorieConsumedData": false, "privacyProtected": false, "moderateIntensityMinutes": 0, "vigorousIntensityMinutes": 0, "floorsAscendedInMeters": 32.202, "floorsDescendedInMeters": 30.996, "floorsAscended": 10.56496, "floorsDescended": 10.16929, "intensityMinutesGoal": 150, "userFloorsAscendedGoal": 10, "minHeartRate": 45, "maxHeartRate": 132, "restingHeartRate": 53, "lastSevenDaysAvgRestingHeartRate": 53, "source": "GARMIN", "averageStressLevel": 28, "maxStressLevel": 90, "stressDuration": 40740, "restStressDuration": 26700, "activityStressDuration": 6660, "uncategorizedStressDuration": 10620, "totalStressDuration": 84720, "lowStressDuration": 36720, "mediumStressDuration": 3120, "highStressDuration": 900, "stressPercentage": 48.09, "restStressPercentage": 31.52, "activityStressPercentage": 7.86, "uncategorizedStressPercentage": 12.54, "lowStressPercentage": 43.34, "mediumStressPercentage": 3.68, "highStressPercentage": 1.06, "stressQualifier": "STRESSFUL", "measurableAwakeDuration": 51180, "measurableAsleepDuration": 22920, "lastSyncTimestampGMT": null, "minAvgHeartRate": 47, "maxAvgHeartRate": 125, "bodyBatteryChargedValue": 0, "bodyBatteryDrainedValue": 0, "bodyBatteryHighestValue": null, "bodyBatteryLowestValue": null, "bodyBatteryMostRecentValue": null, "bodyBatteryDuringSleep": null, "bodyBatteryVersion": 1.0, "abnormalHeartRateAlertsCount": null, "averageSpo2": null, "lowestSpo2": null, "latestSpo2": null, "latestSpo2ReadingTimeGmt": null, "latestSpo2ReadingTimeLocal": null, "averageMonitoringEnvironmentAltitude": null, "restingCaloriesFromActivity": null}