{"userProfileId": 8420505, "totalKilocalories": 2893.0, "activeKilocalories": 1074.0, "bmrKilocalories": 1819.0, "wellnessKilocalories": 2893.0, "burnedKilocalories": 0.0, "consumedKilocalories": null, "remainingKilocalories": 2893.0, "totalSteps": 3331, "netCalorieGoal": null, "totalDistanceMeters": 60538, "wellnessDistanceMeters": 60538, "wellnessActiveKilocalories": 1074.0, "netRemainingKilocalories": 1074.0, "userDailySummaryId": 8420505, "calendarDate": "2018-02-05", "rule": {"typeId": 3, "typeKey": "subscribers"}, "uuid": "e076c01b4c534d0b818b3adb3063efce", "dailyStepGoal": 9630, "wellnessStartTimeGmt": "2018-02-04T13:00:00.0", "wellnessStartTimeLocal": "2018-02-05T00:00:00.0", "wellnessEndTimeGmt": "2018-02-05T13:00:00.0", "wellnessEndTimeLocal": "2018-02-06T00:00:00.0", "durationInMilliseconds": 86400000, "wellnessDescription": null, "highlyActiveSeconds": 1398, "activeSeconds": 3686, "sedentarySeconds": 56176, "sleepingSeconds": 25140, "includesWellnessData": true, "includesActivityData": true, "includesCalorieConsumedData": false, "privacyProtected": false, "moderateIntensityMinutes": 20, "vigorousIntensityMinutes": 13, "floorsAscendedInMeters": 10.207, "floorsDescendedInMeters": 4.585, "floorsAscended": 3.34875, "floorsDescended": 1.50427, "intensityMinutesGoal": 150, "userFloorsAscendedGoal": 10, "minHeartRate": 46, "maxHeartRate": 158, "restingHeartRate": 59, "lastSevenDaysAvgRestingHeartRate": 59, "source": "GARMIN", "averageStressLevel": 29, "maxStressLevel": 99, "stressDuration": 28620, "restStressDuration": 31140, "activityStressDuration": 15180, "uncategorizedStressDuration": 4440, "totalStressDuration": 79380, "lowStressDuration": 19920, "mediumStressDuration": 6480, "highStressDuration": 2220, "stressPercentage": 36.05, "restStressPercentage": 39.23, "activityStressPercentage": 19.12, "uncategorizedStressPercentage": 5.59, "lowStressPercentage": 25.09, "mediumStressPercentage": 8.16, "highStressPercentage": 2.8, "stressQualifier": "BALANCED", "measurableAwakeDuration": 50640, "measurableAsleepDuration": 24300, "lastSyncTimestampGMT": null, "minAvgHeartRate": 48, "maxAvgHeartRate": 156, "bodyBatteryChargedValue": null, "bodyBatteryDrainedValue": null, "bodyBatteryHighestValue": null, "bodyBatteryLowestValue": null, "bodyBatteryMostRecentValue": null, "bodyBatteryDuringSleep": null, "bodyBatteryVersion": null, "abnormalHeartRateAlertsCount": null, "averageSpo2": null, "lowestSpo2": null, "latestSpo2": null, "latestSpo2ReadingTimeGmt": null, "latestSpo2ReadingTimeLocal": null, "averageMonitoringEnvironmentAltitude": null, "restingCaloriesFromActivity": null}