{"userProfileId": 8420505, "totalKilocalories": 2447.0, "activeKilocalories": 616.0, "bmrKilocalories": 1831.0, "wellnessKilocalories": 2447.0, "burnedKilocalories": 0.0, "consumedKilocalories": null, "remainingKilocalories": 2447.0, "totalSteps": 7475, "netCalorieGoal": null, "totalDistanceMeters": 7405, "wellnessDistanceMeters": 7405, "wellnessActiveKilocalories": 616.0, "netRemainingKilocalories": 616.0, "userDailySummaryId": 8420505, "calendarDate": "2016-12-25", "rule": {"typeId": 3, "typeKey": "subscribers"}, "uuid": "356b239af8ff42d6b98355e66417e3cc", "dailyStepGoal": 10555, "wellnessStartTimeGmt": "2016-12-24T13:00:00.0", "wellnessStartTimeLocal": "2016-12-25T00:00:00.0", "wellnessEndTimeGmt": "2016-12-25T13:00:00.0", "wellnessEndTimeLocal": "2016-12-26T00:00:00.0", "durationInMilliseconds": 86400000, "wellnessDescription": null, "highlyActiveSeconds": 1328, "activeSeconds": 10739, "sedentarySeconds": 47453, "sleepingSeconds": 26880, "includesWellnessData": true, "includesActivityData": true, "includesCalorieConsumedData": false, "privacyProtected": false, "moderateIntensityMinutes": 23, "vigorousIntensityMinutes": 17, "floorsAscendedInMeters": 73.78599999999999, "floorsDescendedInMeters": 60.202, "floorsAscended": 24.20801, "floorsDescended": 19.75131, "intensityMinutesGoal": 150, "userFloorsAscendedGoal": 10, "minHeartRate": 46, "maxHeartRate": 191, "restingHeartRate": 46, "lastSevenDaysAvgRestingHeartRate": 54, "source": "GARMIN", "averageStressLevel": null, "maxStressLevel": null, "stressDuration": null, "restStressDuration": null, "activityStressDuration": null, "uncategorizedStressDuration": null, "totalStressDuration": null, "lowStressDuration": null, "mediumStressDuration": null, "highStressDuration": null, "stressPercentage": null, "restStressPercentage": null, "activityStressPercentage": null, "uncategorizedStressPercentage": null, "lowStressPercentage": null, "mediumStressPercentage": null, "highStressPercentage": null, "stressQualifier": null, "measurableAwakeDuration": null, "measurableAsleepDuration": null, "lastSyncTimestampGMT": null, "minAvgHeartRate": 46, "maxAvgHeartRate": 191, "bodyBatteryChargedValue": null, "bodyBatteryDrainedValue": null, "bodyBatteryHighestValue": null, "bodyBatteryLowestValue": null, "bodyBatteryMostRecentValue": null, "bodyBatteryDuringSleep": null, "bodyBatteryVersion": null, "abnormalHeartRateAlertsCount": null, "averageSpo2": null, "lowestSpo2": null, "latestSpo2": null, "latestSpo2ReadingTimeGmt": null, "latestSpo2ReadingTimeLocal": null, "averageMonitoringEnvironmentAltitude": null, "restingCaloriesFromActivity": null}