{"userProfileId": 8420505, "totalKilocalories": 2452.0, "activeKilocalories": 664.0, "bmrKilocalories": 1788.0, "wellnessKilocalories": 2452.0, "burnedKilocalories": null, "consumedKilocalories": null, "remainingKilocalories": 2452.0, "totalSteps": 13665, "netCalorieGoal": 1850, "totalDistanceMeters": 15229, "wellnessDistanceMeters": 15229, "wellnessActiveKilocalories": 664.0, "netRemainingKilocalories": 2514.0, "userDailySummaryId": 8420505, "calendarDate": "2024-04-03", "rule": {"typeId": 3, "typeKey": "subscribers"}, "uuid": "6f7395a4b09145a19e072a7d5221c053", "dailyStepGoal": 9090, "wellnessStartTimeGmt": "2024-04-02T22:00:00.0", "wellnessStartTimeLocal": "2024-04-03T00:00:00.0", "wellnessEndTimeGmt": "2024-04-03T22:00:00.0", "wellnessEndTimeLocal": "2024-04-04T00:00:00.0", "durationInMilliseconds": 86400000, "wellnessDescription": null, "highlyActiveSeconds": 4111, "activeSeconds": 1460, "sedentarySeconds": 53386, "sleepingSeconds": 27443, "includesWellnessData": true, "includesActivityData": true, "includesCalorieConsumedData": false, "privacyProtected": false, "moderateIntensityMinutes": 2, "vigorousIntensityMinutes": 55, "floorsAscendedInMeters": 30.5, "floorsDescendedInMeters": 22.484, "floorsAscended": 10.00656, "floorsDescended": 7.37664, "intensityMinutesGoal": 150, "userFloorsAscendedGoal": 10, "minHeartRate": 47, "maxHeartRate": 153, "restingHeartRate": 51, "lastSevenDaysAvgRestingHeartRate": 53, "source": "GARMIN", "averageStressLevel": 20, "maxStressLevel": 86, "stressDuration": 17700, "restStressDuration": 53220, "activityStressDuration": 5580, "uncategorizedStressDuration": 8640, "totalStressDuration": 85140, "lowStressDuration": 15900, "mediumStressDuration": 1620, "highStressDuration": 180, "stressPercentage": 20.79, "restStressPercentage": 62.51, "activityStressPercentage": 6.55, "uncategorizedStressPercentage": 10.15, "lowStressPercentage": 18.68, "mediumStressPercentage": 1.9, "highStressPercentage": 0.21, "stressQualifier": "CALM", "measurableAwakeDuration": 56460, "measurableAsleepDuration": 20040, "lastSyncTimestampGMT": null, "minAvgHeartRate": 48, "maxAvgHeartRate": 151, "bodyBatteryChargedValue": 57, "bodyBatteryDrainedValue": 65, "bodyBatteryHighestValue": 100, "bodyBatteryLowestValue": 35, "bodyBatteryMostRecentValue": 55, "bodyBatteryDuringSleep": 61, "bodyBatteryVersion": 3.0, "abnormalHeartRateAlertsCount": null, "averageSpo2": 95.0, "lowestSpo2": 86, "latestSpo2": 89, "latestSpo2ReadingTimeGmt": "2024-04-03T22:00:00.0", "latestSpo2ReadingTimeLocal": "2024-04-04T00:00:00.0", "averageMonitoringEnvironmentAltitude": 24.0, "restingCaloriesFromActivity": 68.0, "bodyBatteryDynamicFeedbackEvent": {"eventTimestampGmt": "2024-04-03T17:35:00", "bodyBatteryLevel": "HIGH", "feedbackShortType": "SLEEP_PREPARATION_RECOVERING_AND_INTENSIVE_EXERCISE", "feedbackLongType": "SLEEP_PREPARATION_RECOVERING_AND_INTENSIVE_EXERCISE"}, "endOfDayBodyBatteryDynamicFeedbackEvent": {"eventTimestampGmt": "2024-04-03T20:34:51", "bodyBatteryLevel": "HIGH", "feedbackShortType": "SLEEP_TIME_PASSED_RECOVERING_AND_INTENSIVE_EXERCISE", "feedbackLongType": "SLEEP_TIME_PASSED_RECOVERING_AND_INTENSIVE_EXERCISE"}, "bodyBatteryActivityEventList": [{"eventType": "SLEEP", "eventStartTimeGmt": "2024-04-02T19:23:37", "timezoneOffset": 7200000, "durationInMilliseconds": 29460000, "bodyBatteryImpact": 61, "feedbackType": "NONE", "shortFeedback": "NONE", "deviceId": 3447302851, "activityName": null, "activityType": null, "activityId": null, "eventUpdateTimeGmt": "2024-04-03T03:37:35"}, {"eventType": "RECOVERY", "eventStartTimeGmt": "2024-04-03T06:37:55", "timezoneOffset": 7200000, "durationInMilliseconds": 3180000, "bodyBatteryImpact": 0, "feedbackType": "RECOVERY_BODY_BATTERY_NOT_INCREASE", "shortFeedback": "RESTFUL_PERIOD", "deviceId": 3447302851, "activityName": null, "activityType": null, "activityId": null, "eventUpdateTimeGmt": "2024-04-03T07:33:59"}, {"eventType": "ACTIVITY", "eventStartTimeGmt": "2024-04-03T12:54:08", "timezoneOffset": 7200000, "durationInMilliseconds": 3240000, "bodyBatteryImpact": -14, "feedbackType": "EXERCISE_TRAINING_EFFECT_3", "shortFeedback": "IMPROVING_AEROBIC_BASE", "deviceId": 3447302851, "activityName": "Copenhagen - 12 140-150bpm", "activityType": "running", "activityId": 14715132302, "eventUpdateTimeGmt": "2024-04-03T13:49:14"}], "isJetLagDay": true, "jetLagTripName": "K\u00f8benhavn \u00d8 - Istanbul", "avgWakingRespirationValue": 14.0, "highestRespirationValue": 34.0, "lowestRespirationValue": 9.0, "latestRespirationValue": 16.0, "latestRespirationTimeGMT": "2024-04-03T21:59:00.0"}